README.md
setup.py
./aperf/__init__.py
./aperf/cost.py
./aperf/main.py
./aperf/profiler.py
./aperf/task_graph.py
aperf/__init__.py
aperf/cost.py
aperf/main.py
aperf/profiler.py
aperf/task_graph.py
aperf.egg-info/PKG-INFO
aperf.egg-info/SOURCES.txt
aperf.egg-info/dependency_links.txt
aperf.egg-info/entry_points.txt
aperf.egg-info/requires.txt
aperf.egg-info/top_level.txt
data/perf.INFO
docs/imgs/timecost.png
docs/imgs/timeline.png